README.md
VERSION
setup.py
pihy/AtlasI2C.py
pihy/AtlasPH.py
pihy/AtlasPump.py
pihy/Log.py
pihy/__init__.py
pihy/__main__.py
pihy/app.py
pihy/camera.py
pihy/ip.py
pihy/ph_cal_10.py
pihy/ph_cal_4.py
pihy/ph_cal_7.py
pihy/ph_cal_clear.py
pihy/x.py
pihy.egg-info/PKG-INFO
pihy.egg-info/SOURCES.txt
pihy.egg-info/dependency_links.txt
pihy.egg-info/entry_points.txt
pihy.egg-info/not-zip-safe
pihy.egg-info/requires.txt
pihy.egg-info/top_level.txt