Metadata-Version: 1.0
Name: pihy
Version: 0.2.110
Summary: The funniest joke in the world
Home-page: http://github.com/raubreywhite/pihy
Author: Richard
Author-email: w@rwhite.no
License: MIT
Platform: UNKNOWN
